rehydra/__init__.py
rehydra/compose.py
rehydra/errors.py
rehydra/initialize.py
rehydra/main.py
rehydra/py.typed
rehydra/types.py
rehydra/utils.py
rehydra/version.py
rehydra/_internal/__init__.py
rehydra/_internal/callbacks.py
rehydra/_internal/config_loader_impl.py
rehydra/_internal/config_repository.py
rehydra/_internal/config_search_path_impl.py
rehydra/_internal/defaults_list.py
rehydra/_internal/deprecation_warning.py
rehydra/_internal/rehydra.py
rehydra/_internal/sources_registry.py
rehydra/_internal/utils.py
rehydra/_internal/core_plugins/__init__.py
rehydra/_internal/core_plugins/bash_completion.py
rehydra/_internal/core_plugins/basic_launcher.py
rehydra/_internal/core_plugins/basic_sweeper.py
rehydra/_internal/core_plugins/file_config_source.py
rehydra/_internal/core_plugins/fish_completion.py
rehydra/_internal/core_plugins/importlib_resources_config_source.py
rehydra/_internal/core_plugins/structured_config_source.py
rehydra/_internal/core_plugins/zsh_completion.py
rehydra/_internal/grammar/__init__.py
rehydra/_internal/grammar/functions.py
rehydra/_internal/grammar/grammar_functions.py
rehydra/_internal/grammar/utils.py
rehydra/_internal/instantiate/__init__.py
rehydra/_internal/instantiate/_instantiate2.py
rehydra/conf/__init__.py
rehydra/conf/rehydra/env/default.yaml
rehydra/conf/rehydra/help/default.yaml
rehydra/conf/rehydra/job_logging/default.yaml
rehydra/conf/rehydra/job_logging/disabled.yaml
rehydra/conf/rehydra/job_logging/none.yaml
rehydra/conf/rehydra/job_logging/stdout.yaml
rehydra/conf/rehydra/output/default.yaml
rehydra/conf/rehydra/rehydra_help/default.yaml
rehydra/conf/rehydra/rehydra_logging/default.yaml
rehydra/conf/rehydra/rehydra_logging/disabled.yaml
rehydra/conf/rehydra/rehydra_logging/none.yaml
rehydra/conf/rehydra/rehydra_logging/rehydra_debug.yaml
rehydra/core/__init__.py
rehydra/core/config_loader.py
rehydra/core/config_search_path.py
rehydra/core/config_store.py
rehydra/core/default_element.py
rehydra/core/global_rehydra.py
rehydra-1.3.5.dist-info/METADATA
rehydra-1.3.5.dist-info/WHEEL
rehydra-1.3.5.dist-info/entry_points.txt
rehydra-1.3.5.dist-info/top_level.txt
rehydra-1.3.5.dist-info/RECORD
