Metadata-Version: 2.1
Name: rehydra
Version: 1.3.5
Summary: A framework for configuring immensely complex applications with relative elegance
Home-page: https://gitflic.ru/project/aidynamicaction/rehydra?branch=rehydra-main
Author: Grigory Yaremenko, Georgiy Malaniya, Anton Bolychev, Pavel Osinenko
Author-email: p.osinenko@yandex.ru
License: UNKNOWN
Keywords: command-line configuration yaml tab-completion
Platform: UNKNOWN
Classifier: License :: OSI Approved :: MIT License
Classifier: Development Status :: 4 - Beta
Classifier: Programming Language :: Python :: 3.7
Classifier: Programming Language :: Python :: 3.8
Classifier: Programming Language :: Python :: 3.9
Classifier: Programming Language :: Python :: 3.10
Classifier: Programming Language :: Python :: 3.11
Classifier: Operating System :: POSIX :: Linux
Classifier: Operating System :: MacOS
Classifier: Operating System :: Microsoft :: Windows
Requires-Dist: omegaconf (<2.4,>=2.2)
Requires-Dist: antlr4-python3-runtime (==4.9.*)
Requires-Dist: rich (==13.3.1)
Requires-Dist: packaging
Requires-Dist: importlib-resources ; python_version < "3.9"
